kuryr_tempest_plugin/README.rst
kuryr_tempest_plugin/__init__.py
kuryr_tempest_plugin/config.py
kuryr_tempest_plugin/plugin.py
kuryr_tempest_plugin/tests/__init__.py
kuryr_tempest_plugin/tests/scenario/README.rst
kuryr_tempest_plugin/tests/scenario/__init__.py
kuryr_tempest_plugin/tests/scenario/base.py
kuryr_tempest_plugin/tests/scenario/base_network_policy.py
kuryr_tempest_plugin/tests/scenario/consts.py
kuryr_tempest_plugin/tests/scenario/test_annotation_project.py
kuryr_tempest_plugin/tests/scenario/test_cross_ping.py
kuryr_tempest_plugin/tests/scenario/test_cross_ping_multi_worker.py
kuryr_tempest_plugin/tests/scenario/test_daemon.py
kuryr_tempest_plugin/tests/scenario/test_ha.py
kuryr_tempest_plugin/tests/scenario/test_kuryr_restart.py
kuryr_tempest_plugin/tests/scenario/test_namespace.py
kuryr_tempest_plugin/tests/scenario/test_network_policy.py
kuryr_tempest_plugin/tests/scenario/test_npwg_multi_vif.py
kuryr_tempest_plugin/tests/scenario/test_port_pool.py
kuryr_tempest_plugin/tests/scenario/test_service.py
kuryr_tempest_plugin-0.16.0.dist-info/AUTHORS
kuryr_tempest_plugin-0.16.0.dist-info/LICENSE
kuryr_tempest_plugin-0.16.0.dist-info/METADATA
kuryr_tempest_plugin-0.16.0.dist-info/WHEEL
kuryr_tempest_plugin-0.16.0.dist-info/entry_points.txt
kuryr_tempest_plugin-0.16.0.dist-info/pbr.json
kuryr_tempest_plugin-0.16.0.dist-info/top_level.txt
kuryr_tempest_plugin-0.16.0.dist-info/RECORD
